{
  "cards": [
    {
      "id": "5e8312a9-b45a-49a1-b175-17deae8fcf28",
      "title": "dasasd",
      "descriptionHtml": "",
      "location": {
        "day": "thu",
        "period": "afternoon"
      },
      "order": 0,
      "date": null,
      "time": null,
      "hasDate": false,
      "priority": null,
      "status": "todo",
      "projectId": null,
      "checklist": [],
      "createdAt": "2026-02-10T02:59:10.100Z",
      "updatedAt": "2026-02-19T22:10:29.859Z"
    },
    {
      "id": "5be6248a-7dcf-4805-bdd4-3cb6653b37b0",
      "title": "sa",
      "descriptionHtml": "",
      "location": {
        "day": null,
        "period": null
      },
      "order": 1770692364677,
      "date": null,
      "time": null,
      "hasDate": false,
      "priority": null,
      "status": "todo",
      "projectId": null,
      "checklist": [],
      "createdAt": "2026-02-10T02:59:24.677Z",
      "updatedAt": "2026-02-10T02:59:24.677Z"
    }
  ]
}